pygedcom/__init__.py
pygedcom/gedcom_parser.py
pygedcom/elements/__init__.py
pygedcom/elements/element.py
pygedcom/elements/mapping.json
pygedcom/elements/rootElements/__init__.py
pygedcom/elements/rootElements/family.py
pygedcom/elements/rootElements/head.py
pygedcom/elements/rootElements/individual.py
pygedcom/elements/rootElements/note.py
pygedcom/elements/rootElements/object.py
pygedcom/elements/rootElements/repository.py
pygedcom/elements/rootElements/rootElement.py
pygedcom/elements/rootElements/source.py
pygedcom/elements/rootElements/submitter.py
pygedcom/elements/subElements/__init__.py
pygedcom/elements/subElements/commonEvent.py
pygedcom/elements/subElements/date.py
pygedcom/elements/subElements/map.py
pygedcom/elements/subElements/place.py
pygedcom-0.2.3.dist-info/METADATA
pygedcom-0.2.3.dist-info/WHEEL
pygedcom-0.2.3.dist-info/licenses/LICENSE
pygedcom-0.2.3.dist-info/RECORD
