Metadata-Version: 2.3
Name: pygedcom
Version: 0.2.3
Summary: A gedcom utility library
Project-URL: Homepage, https://github.com/topetit/pygedcom
Project-URL: Bug Tracker, https://github.com/topetit/pygedcom/issues
Author-email: Theo Petit <theo.p83@gmail.com>
License-File: LICENSE
Classifier: License :: OSI Approved :: MIT License
Classifier: Operating System :: OS Independent
Classifier: Programming Language :: Python :: 3
Requires-Python: >=3.7
